[
    {
        "key": "sb",
        "value": "krT6Zz63dX9cNO18MNP9ZBon",
        "domain": "facebook.com",
        "path": "/",
        "hostOnly": false,
        "creation": "2025-08-26T17:13:25.767Z",
        "lastAccessed": "2025-08-26T17:13:25.767Z"
    },
    {
        "key": "ps_l",
        "value": "1",
        "domain": "facebook.com",
        "path": "/",
        "hostOnly": false,
        "creation": "2025-08-26T17:13:25.767Z",
        "lastAccessed": "2025-08-26T17:13:25.767Z"
    },
    {
        "key": "ps_n",
        "value": "1",
        "domain": "facebook.com",
        "path": "/",
        "hostOnly": false,
        "creation": "2025-08-26T17:13:25.767Z",
        "lastAccessed": "2025-08-26T17:13:25.767Z"
    },
    {
        "key": "wl_cbv",
        "value": "v2%3Bclient_version%3A2838%3Btimestamp%3A1749142585",
        "domain": "facebook.com",
        "path": "/",
        "hostOnly": false,
        "creation": "2025-08-26T17:13:25.767Z",
        "lastAccessed": "2025-08-26T17:13:25.767Z"
    },
    {
        "key": "locale",
        "value": "en_US",
        "domain": "facebook.com",
        "path": "/",
        "hostOnly": false,
        "creation": "2025-08-26T17:13:25.768Z",
        "lastAccessed": "2025-08-26T17:13:25.768Z"
    },
    {
        "key": "datr",
        "value": "3eqtaImGZuuvKNgOF5Z6JfgK",
        "domain": "facebook.com",
        "path": "/",
        "hostOnly": false,
        "creation": "2025-08-26T17:13:25.768Z",
        "lastAccessed": "2025-08-26T17:13:25.768Z"
    },
    {
        "key": "wd",
        "value": "980x1688",
        "domain": "facebook.com",
        "path": "/",
        "hostOnly": false,
        "creation": "2025-08-26T17:13:25.768Z",
        "lastAccessed": "2025-08-26T17:13:25.768Z"
    },
    {
        "key": "c_user",
        "value": "61552814848384",
        "domain": "facebook.com",
        "path": "/",
        "hostOnly": false,
        "creation": "2025-08-26T17:13:25.768Z",
        "lastAccessed": "2025-08-26T17:13:25.768Z"
    },
    {
        "key": "xs",
        "value": "24%3A6lwkPu3caYaSbg%3A2%3A1756228393%3A-1%3A-1",
        "domain": "facebook.com",
        "path": "/",
        "hostOnly": false,
        "creation": "2025-08-26T17:13:25.768Z",
        "lastAccessed": "2025-08-26T17:13:25.768Z"
    },
    {
        "key": "fr",
        "value": "1sId6YNw1ZzbYhC5k.AWfbtrXtbKJ3afdayP-KyRM_fWCqi-A3pPjKlimk6gEnvMUtbhE.BorcYS..AAA.0.0.Boress.AWeCkz0bPQ_IK7Q9E6bi2eiReYQ",
        "domain": "facebook.com",
        "path": "/",
        "hostOnly": false,
        "creation": "2025-08-26T17:13:25.768Z",
        "lastAccessed": "2025-08-26T17:13:25.768Z"
    }
]
